scinot/__init__.py
scinot/main.py
scinot/test_scinot.py
scinot-0.0.11.dist-info/METADATA
scinot-0.0.11.dist-info/RECORD
scinot-0.0.11.dist-info/WHEEL
scinot-0.0.11.dist-info/top_level.txt
