Metadata-Version: 2.1
Name: scinot
Version: 0.0.11
Summary: Display numbers in scientific notation.
Home-page: https://github.com/David-OConnor/scinot
Author: David O'Connor
Author-email: david.alan.oconnor@gmail.com
License: MIT
Keywords: scientific notation,exponential,REPL
Platform: UNKNOWN
Classifier: Programming Language :: Python :: 3 :: Only
Classifier: License :: OSI Approved :: MIT License
Classifier: Operating System :: OS Independent
Classifier: Topic :: Scientific/Engineering
Requires-Dist: colorama
